rlmusician/__init__.py
rlmusician/__main__.py
rlmusician/agent/__init__.py
rlmusician/agent/monte_carlo_beam_search.py
rlmusician/configs/default_config.yml
rlmusician/configs/sinethesizer_presets.yml
rlmusician/environment/__init__.py
rlmusician/environment/environment.py
rlmusician/environment/evaluation.py
rlmusician/environment/piece.py
rlmusician/environment/rules.py
rlmusician/utils/__init__.py
rlmusician/utils/io.py
rlmusician/utils/misc.py
rlmusician/utils/music_theory.py
tests/__init__.py
tests/conftest.py
tests/agent/__init__.py
tests/agent/test_monte_carlo_beam_search.py
tests/environment/__init__.py
tests/environment/test_environment.py
tests/environment/test_evaluation.py
tests/environment/test_piece.py
tests/environment/test_rules.py
tests/utils/__init__.py
tests/utils/test_io.py
tests/utils/test_misc.py
tests/utils/test_music_theory.py
rl_musician-0.4.6.dist-info/LICENSE
rl_musician-0.4.6.dist-info/METADATA
rl_musician-0.4.6.dist-info/WHEEL
rl_musician-0.4.6.dist-info/top_level.txt
rl_musician-0.4.6.dist-info/RECORD
