Metadata-Version: 2.1
Name: rl-musician
Version: 0.4.6
Summary: Composition of music with reinforcement learning.
Home-page: https://github.com/Nikolay-Lysenko/rl-musician
Author: Nikolay Lysenko
Author-email: nikolay-lysenco@yandex.ru
License: MIT
Keywords: ai_music,algorithmic_composition,counterpoint,reinforcement_learning
Platform: UNKNOWN
Classifier: Development Status :: 4 - Beta
Classifier: Intended Audience :: Developers
Classifier: Topic :: Artistic Software
Classifier: License :: OSI Approved :: MIT License
Classifier: Programming Language :: Python :: 3
Requires-Python: >=3.6
License-File: LICENSE
Requires-Dist: gym
Requires-Dist: numpy
Requires-Dist: pretty-midi
Requires-Dist: PyYAML
Requires-Dist: sinethesizer (<0.7,>=0.6)
